pinetoken/__init__.py
pinetoken/__main__.py
pinetoken/main.py
pinetoken/function/__init__.py
pinetoken/function/add.py
pinetoken/function/crypto.py
pinetoken/function/delete.py
pinetoken/function/export.py
pinetoken/function/init.py
pinetoken/function/list.py
pinetoken/function/show.py
pinetoken/function/utils.py
pinetoken-0.0.2.dist-info/licenses/LICENSE
pinetoken-0.0.2.dist-info/METADATA
pinetoken-0.0.2.dist-info/WHEEL
pinetoken-0.0.2.dist-info/entry_points.txt
pinetoken-0.0.2.dist-info/top_level.txt
pinetoken-0.0.2.dist-info/RECORD
