Metadata-Version: 2.4
Name: pinetoken
Version: 0.0.2
Summary: A secure and simple CLI token manager with encryption support.
Home-page: https://github.com/openpineapletools/pinetoken
Author: openpineaplehub
Author-email: openpineaplehub <openpineaple@gmail.com>
License: MIT
Project-URL: Homepage, https://github.com/openpineapletools/pinetoken
Project-URL: Repository, https://github.com/openpineapletools/pinetoken
Project-URL: Issues, https://github.com/openpineapletools/pinetoken/issues
Keywords: CLI,token,manager,security,encryption,password
Classifier: Programming Language :: Python :: 3
Classifier: Operating System :: OS Independent
Classifier: License :: OSI Approved :: MIT License
Classifier: Environment :: Console
Classifier: Intended Audience :: Developers
Classifier: Topic :: Security :: Cryptography
Requires-Python: >=3.8
License-File: LICENSE
Requires-Dist: cryptography>=41.0.3
Requires-Dist: tabulate>=0.9.0
Dynamic: author
Dynamic: home-page
Dynamic: license-file
Dynamic: requires-python
